deno_sandbox/__init__.py
deno_sandbox/bridge.py
deno_sandbox/client.py
deno_sandbox/console.py
deno_sandbox/options.py
deno_sandbox/py.typed
deno_sandbox/rpc.py
deno_sandbox/sandbox.py
deno_sandbox/sandbox_generated.py
deno_sandbox/transport.py
deno_sandbox/volumes.py
deno_sandbox-0.2.0.dist-info/WHEEL
deno_sandbox-0.2.0.dist-info/METADATA
deno_sandbox-0.2.0.dist-info/RECORD
