Metadata-Version: 2.3
Name: deno-sandbox
Version: 0.2.0
Summary: Deno Sandbox Python SDK
Author: The Deno Team
Author-email: The Deno Team <support@deno.com>
Requires-Dist: httpx>=0.28.1
Requires-Dist: pydantic>=2.12.5
Requires-Dist: uuid>=1.30
Requires-Dist: websockets>=15.0.1
Requires-Python: >=3.14
